uav_hud/__init__.py
uav_hud/frame_modifier.py
uav_hud-0.0.2.dist-info/LICENSE
uav_hud-0.0.2.dist-info/METADATA
uav_hud-0.0.2.dist-info/WHEEL
uav_hud-0.0.2.dist-info/top_level.txt
uav_hud-0.0.2.dist-info/RECORD
